stopwatch/__init__.py
stopwatch/exceptions.py
stopwatch/stopwatch.py
ez_stopwatch-1.0.1.dist-info/LICENSE
ez_stopwatch-1.0.1.dist-info/METADATA
ez_stopwatch-1.0.1.dist-info/WHEEL
ez_stopwatch-1.0.1.dist-info/top_level.txt
ez_stopwatch-1.0.1.dist-info/RECORD
