Metadata-Version: 2.1
Name: ez-stopwatch
Version: 1.0.1
Summary: A Stopwatch for timing blocks of code
Home-page: https://github.com/shner-elmo/Stopwatch
Author: Shneor Elmaleh
Classifier: Programming Language :: Python :: 3
Classifier: License :: OSI Approved :: MIT License
Classifier: Operating System :: OS Independent
Requires-Python: >=3.7
License-File: LICENSE
